yourscirpt_test/__init__.py
yourscirpt_test/myClickDemo.py
yourscirpt_test/yourscript.py
yourscript_test-0.1.5.dist-info/LICENSE
yourscript_test-0.1.5.dist-info/METADATA
yourscript_test-0.1.5.dist-info/WHEEL
yourscript_test-0.1.5.dist-info/top_level.txt
yourscript_test-0.1.5.dist-info/RECORD
